minimodal/__init__.py
minimodal/cli.py
minimodal/mcp_cli.py
minimodal/mcp_server.py
minimodal/modal_integration.py
minimodal-0.2.0.dist-info/licenses/LICENSE
minimodal-0.2.0.dist-info/METADATA
minimodal-0.2.0.dist-info/WHEEL
minimodal-0.2.0.dist-info/entry_points.txt
minimodal-0.2.0.dist-info/top_level.txt
minimodal-0.2.0.dist-info/RECORD
