Metadata-Version: 2.4
Name: minimodal
Version: 0.2.0
Summary: A simple tool to compile and run CUDA kernels on local GPUs or Modal cloud infrastructure, now with MCP server support
Author-email: Your Name <you@example.com>
License-Expression: MIT
Project-URL: Homepage, https://github.com/yourusername/minimodal
Project-URL: Repository, https://github.com/yourusername/minimodal
Project-URL: Issues, https://github.com/yourusername/minimodal/issues
Keywords: cuda,gpu,compilation,kernel,mcp,model-context-protocol
Classifier: Development Status :: 3 - Alpha
Classifier: Intended Audience :: Developers
Classifier: Programming Language :: Python :: 3
Classifier: Programming Language :: Python :: 3.8
Classifier: Programming Language :: Python :: 3.9
Classifier: Programming Language :: Python :: 3.10
Classifier: Programming Language :: Python :: 3.11
Classifier: Programming Language :: Python :: 3.12
Classifier: Topic :: Software Development :: Build Tools
Classifier: Topic :: System :: Hardware
Requires-Python: >=3.8
License-File: LICENSE
Requires-Dist: click>=8.0.0
Requires-Dist: modal>=0.60.0
Requires-Dist: mcp>=1.0.0
Requires-Dist: starlette>=0.27.0
Requires-Dist: uvicorn>=0.24.0
Requires-Dist: anyio>=4.0.0
Dynamic: license-file
